{
  "il2cpp_init": "HTZhzFUqbyI",
  "il2cpp_init_utf16": "qoVlbiFsGXx",
  "il2cpp_shutdown": "tYzvNGbDsMx",
  "il2cpp_set_config_dir": "vhjkKBjQVtL",
  "il2cpp_set_data_dir": "rHHVCmg_sLy",
  "il2cpp_set_temp_dir": "ZhdQhYTIEaB",
  "il2cpp_set_commandline_arguments": "MBSvbDtRTFL",
  "il2cpp_set_commandline_arguments_utf16": "epNfXefj_Et",
  "il2cpp_set_config_utf16": "C__sELeWPny",
  "il2cpp_set_config": "QDvGpOZVOBJ",
  "il2cpp_set_memory_callbacks": "Vh_xQ_hMQj_",
  "il2cpp_memory_pool_set_region_size": "LFcroQJmBZA",
  "il2cpp_memory_pool_get_region_size": "KVJzKcSFlJC",
  "il2cpp_get_corlib": "sjzlT_XnTUJ",
  "il2cpp_add_internal_call": "FuWwXHdfVmg",
  "il2cpp_resolve_icall": "XeTnlylOMJH",
  "il2cpp_alloc": "FZdIqetpuQU",
  "il2cpp_free": "XCgvOtBXscq",
  "il2cpp_array_class_get": "plAzJHJWGdr",
  "il2cpp_array_length": "Qkp_ETFuByA",
  "il2cpp_array_get_byte_length": "VcJrQGBhlHp",
  "il2cpp_array_new": "UBokIFRPSGK",
  "il2cpp_array_new_specific": "eTfWALVduXb",
  "il2cpp_array_new_full": "kbFvKHbwKzQ",
  "il2cpp_bounded_array_class_get": "rPWdSceBvYK",
  "il2cpp_array_element_size": "UzXSmYywMeB",
  "il2cpp_assembly_get_image": "POgshCTdihb",
  "il2cpp_class_for_each": "LjyZrNCEdyt",
  "il2cpp_class_enum_basetype": "_DRIqVlxmPU",
  "il2cpp_class_is_inited": "vJlzsSrmryZ",
  "il2cpp_class_is_generic": "ZREDbKPEu_E",
  "il2cpp_class_is_inflated": "TpErjWlddTg",
  "il2cpp_class_is_assignable_from": "XqEChdOleBJ",
  "il2cpp_class_is_subclass_of": "kIYTYOjXGEl",
  "il2cpp_class_has_parent": "bIiQXHejAAF",
  "il2cpp_class_from_il2cpp_type": "BUkTGiGpZHZ",
  "il2cpp_class_from_name": "_FynQQpdJRi",
  "il2cpp_class_from_system_type": "YoManmlvKKt",
  "il2cpp_class_get_element_class": "wcOXQxKDZBb",
  "il2cpp_class_get_events": "GfZETJuKkPZ",
  "il2cpp_class_get_fields": "ZsogBUwOW_H",
  "il2cpp_class_get_nested_types": "MDfWnhLsIuD",
  "il2cpp_class_get_interfaces": "xcIeVLtZLdP",
  "il2cpp_class_get_properties": "fXjdue_nHOo",
  "il2cpp_class_get_property_from_name": "xulOjMIqpJU",
  "il2cpp_class_get_field_from_name": "gDnhWDbYSpH",
  "il2cpp_class_get_methods": "C_sFjnoxmJP",
  "il2cpp_class_get_method_from_name": "zFDBHCNr_ab",
  "il2cpp_class_get_name": "ldruoCazrsH",
  "il2cpp_type_get_name_chunked": "VGIYOYVkcvV",
  "il2cpp_class_get_namespace": "DoLhzKUiCuF",
  "il2cpp_class_get_parent": "etmKsiTmwMr",
  "il2cpp_class_get_declaring_type": "kWKDjXfyvvX",
  "il2cpp_class_instance_size": "SHn_oGzMfjE",
  "il2cpp_class_num_fields": "CURIiakmQlg",
  "il2cpp_class_is_valuetype": "xuMaRMxoRHs",
  "il2cpp_class_value_size": "ltXByksyBfL",
  "il2cpp_class_is_blittable": "OFROGbCZOQu",
  "il2cpp_class_get_flags": "joypOCUltlZ",
  "il2cpp_class_is_abstract": "RMMjmAJQWDm",
  "il2cpp_class_is_interface": "btyVyvjJMkL",
  "il2cpp_class_array_element_size": "ohiYeLoWZMn",
  "il2cpp_class_from_type": "SgxsgjhGsvZ",
  "il2cpp_class_get_type": "ZvKGDd_NDoo",
  "il2cpp_class_get_type_token": "efsmxfkSzEz",
  "il2cpp_class_has_attribute": "BSYXKQzVjrL",
  "il2cpp_class_has_references": "ZeLAgGAzfXL",
  "il2cpp_class_is_enum": "nplNOiOk_dl",
  "il2cpp_class_get_image": "IkFWpxPyv_S",
  "il2cpp_class_get_assemblyname": "wTExMDpWEuj",
  "il2cpp_class_get_rank": "aGEdAzQUhYN",
  "il2cpp_class_get_data_size": "DrUFmmmBDWX",
  "il2cpp_class_get_static_field_data": "MejFQHnltE_",
  "il2cpp_stats_dump_to_file": "uRRca_WUjqR",
  "il2cpp_stats_get_value": "rjVsFyALeJ_",
  "il2cpp_domain_get": "oLZW_adTkez",
  "il2cpp_domain_assembly_open": "cDiORsOLZcf",
  "il2cpp_domain_get_assemblies": "NwJEiIRXxTg",
  "il2cpp_raise_exception": "_eSnxcUtsMH",
  "il2cpp_exception_from_name_msg": "TasyEWrnaeS",
  "il2cpp_get_exception_argument_null": "jkkKVypqlSz",
  "il2cpp_format_exception": "qQTRbuotPpa",
  "il2cpp_format_stack_trace": "uKcClufkuJF",
  "il2cpp_unhandled_exception": "__RWkB_ZUue",
  "il2cpp_native_stack_trace": "OMxoTYTYpbS",
  "il2cpp_field_get_flags": "sZwREtKVmfo",
  "il2cpp_field_get_from_reflection": "tCIcFcPiLks",
  "il2cpp_field_get_name": "OqatnUXLHFK",
  "il2cpp_field_get_parent": "FXElsSCgZbp",
  "il2cpp_field_get_object": "KnloSayKTSG",
  "il2cpp_field_get_offset": "NyOKycomTwf",
  "il2cpp_field_get_type": "_NBDPEWzGGc",
  "il2cpp_field_get_value": "RQdrbIFUGtl",
  "il2cpp_field_get_value_object": "XqxVdzWNXRk",
  "il2cpp_field_has_attribute": "SccqrTianxm",
  "il2cpp_field_set_value": "fpLxWTTJbOn",
  "il2cpp_field_static_get_value": "hPyJiLZPBML",
  "il2cpp_field_static_set_value": "bqzNVHGJeLw",
  "il2cpp_field_set_value_object": "BX_BvlNhsEA",
  "il2cpp_field_is_literal": "QFAhhBGdHJa",
  "il2cpp_gc_collect": "_XJZWSbQGCQ",
  "il2cpp_gc_collect_a_little": "iaLaGJWMhWT",
  "il2cpp_gc_start_incremental_collection": "EMelUVTbKqB",
  "il2cpp_gc_disable": "zmUEb_czzXM",
  "il2cpp_gc_enable": "fKkXveULdRu",
  "il2cpp_gc_is_disabled": "qpKskRoQtWC",
  "il2cpp_gc_set_mode": "AXVijbJkqPb",
  "il2cpp_gc_get_max_time_slice_ns": "bcRUmiPUkJQ",
  "il2cpp_gc_set_max_time_slice_ns": "YEY_sK_GeTR",
  "il2cpp_gc_is_incremental": "tEhwdIrbQBj",
  "il2cpp_gc_get_used_size": "KSvHJlZOBVW",
  "il2cpp_gc_get_heap_size": "hgewKrAuAFe",
  "il2cpp_gc_wbarrier_set_field": "qcXAUDteXzE",
  "il2cpp_gc_has_strict_wbarriers": "cxdYfUHVJXE",
  "il2cpp_gc_set_external_allocation_tracker": "UOgZkEBdiBc",
  "il2cpp_gc_set_external_wbarrier_tracker": "RQXExg_VVpT",
  "il2cpp_gc_foreach_heap": "_r_VmmWpxuj",
  "il2cpp_stop_gc_world": "OYlrjkOKtMT",
  "il2cpp_start_gc_world": "iWmhCHRoMYM",
  "il2cpp_gc_alloc_fixed": "JAiCxmiWJNX",
  "il2cpp_gc_free_fixed": "uqeGkHkw_Wz",
  "il2cpp_gchandle_new": "ibBM_TqqnIC",
  "il2cpp_gchandle_new_weakref": "dFECL_qedRi",
  "il2cpp_gchandle_get_target": "gVBiBHdXpBR",
  "il2cpp_gchandle_free": "kNJNcFLmial",
  "il2cpp_gchandle_foreach_get_target": "PcRsRPotJzW",
  "il2cpp_object_header_size": "BcGq_HbEKks",
  "il2cpp_array_object_header_size": "gWctkFKDAdh",
  "il2cpp_offset_of_array_length_in_array_object_header": "TSeDdtmVdBd",
  "il2cpp_offset_of_array_bounds_in_array_object_header": "UDlpNKstoYz",
  "il2cpp_allocation_granularity": "NzyMdLIQibx",
  "il2cpp_unity_liveness_allocate_struct": "nX_YiNXTwXQ",
  "il2cpp_unity_liveness_calculation_from_root": "IAZWERBoBVE",
  "il2cpp_unity_liveness_calculation_from_statics": "ZcFuBrTnVLg",
  "il2cpp_unity_liveness_finalize": "uQOeAkJqHox",
  "il2cpp_unity_liveness_free_struct": "MpekTxoGYrL",
  "il2cpp_method_get_return_type": "nQgDODLRjTy",
  "il2cpp_method_get_declaring_type": "IVdIZpunkDS",
  "il2cpp_method_get_name": "RE_kGqIahDL",
  "il2cpp_method_get_from_reflection": "XDzbblKWwRz",
  "il2cpp_method_get_object": "sEynSOuYJqe",
  "il2cpp_method_is_generic": "ZTEvIWrjCNP",
  "il2cpp_method_is_inflated": "LNFNTdeMKVy",
  "il2cpp_method_is_instance": "vMUhxYUnONC",
  "il2cpp_method_get_param_count": "FkbMUewqdi_",
  "il2cpp_method_get_param": "hbnwoElhWeN",
  "il2cpp_method_get_class": "fVwvrTWYNFz",
  "il2cpp_method_has_attribute": "JKvfNfzuDyr",
  "il2cpp_method_get_flags": "LVHsCxFvpst",
  "il2cpp_method_get_token": "PIQQWcuRxEi",
  "il2cpp_method_get_param_name": "SEIQs_nzuDv",
  "il2cpp_property_get_flags": "BoJeHJPolWw",
  "il2cpp_property_get_get_method": "OuiIYKtlBnj",
  "il2cpp_property_get_set_method": "rbcwrGgAJIu",
  "il2cpp_property_get_name": "DTazSWR_qlH",
  "il2cpp_property_get_parent": "rDvgGpEPLoY",
  "il2cpp_object_get_class": "klGwuyeIQkv",
  "il2cpp_object_get_size": "FynhINlfRuh",
  "il2cpp_object_get_virtual_method": "DZBPdpWfJfz",
  "il2cpp_object_new": "i_JUuXlivlj",
  "il2cpp_object_unbox": "wlUQhDWJXZO",
  "il2cpp_value_box": "sNDdngreJWh",
  "il2cpp_monitor_enter": "_YeEsUUkFB_",
  "il2cpp_monitor_try_enter": "aWZhjiZVSMb",
  "il2cpp_monitor_exit": "V_Y_nhUeBJh",
  "il2cpp_monitor_pulse": "JMYXOFfAaFB",
  "il2cpp_monitor_pulse_all": "tFNHIBabSjA",
  "il2cpp_monitor_wait": "vcTwDAInYAO",
  "il2cpp_monitor_try_wait": "FJUJizOYyhy",
  "il2cpp_runtime_invoke": "paEOVTMrMmF",
  "il2cpp_runtime_invoke_convert_args": "TRmQ_jliWeM",
  "il2cpp_runtime_class_init": "INVYFFTfnPE",
  "il2cpp_runtime_object_init": "EJBDNlWOLEm",
  "il2cpp_runtime_object_init_exception": "UdcrsuNvZ_V",
  "il2cpp_runtime_unhandled_exception_policy_set": "vznOVgDtXBz",
  "il2cpp_string_length": "VnrQFtsjNGO",
  "il2cpp_string_chars": "opsjveARGwR",
  "il2cpp_string_new": "toAxPmXmsSQ",
  "il2cpp_string_new_len": "dRGWhJuCO_p",
  "il2cpp_string_new_utf16": "WJrHRStiUww",
  "il2cpp_string_new_wrapper": "tQOCYQPwywR",
  "il2cpp_string_intern": "cskBqD_rMcf",
  "il2cpp_string_is_interned": "seLmOxYIGez",
  "il2cpp_thread_current": "bCLPdbvuPbB",
  "il2cpp_thread_attach": "abjssTWAByd",
  "il2cpp_thread_detach": "XmtwuvjISVa",
  "il2cpp_is_vm_thread": "jdLXtNpQAjb",
  "il2cpp_current_thread_walk_frame_stack": "ooqxBxUWDII",
  "il2cpp_thread_walk_frame_stack": "qvJC_OFgUSD",
  "il2cpp_current_thread_get_top_frame": "ECHfVl_HrrB",
  "il2cpp_thread_get_top_frame": "PguojZlreZK",
  "il2cpp_current_thread_get_frame_at": "NdDZKpgfMsS",
  "il2cpp_thread_get_frame_at": "DmSvZwFrBxj",
  "il2cpp_current_thread_get_stack_depth": "GpJefdPulSA",
  "il2cpp_thread_get_stack_depth": "OQYWcW_VMRo",
  "il2cpp_override_stack_backtrace": "daWANeeQeIo",
  "il2cpp_type_get_object": "NAnMhFYhuZX",
  "il2cpp_type_get_type": "NZdnYJmlbxC",
  "il2cpp_type_get_class_or_element_class": "cnItCfiWDEW",
  "il2cpp_type_get_name": "NWgOEtlxDFO",
  "il2cpp_type_is_byref": "znTHjwxVnGV",
  "il2cpp_type_get_attrs": "KHUREkhodKV",
  "il2cpp_type_equals": "sWnbUhFosbt",
  "il2cpp_type_get_assembly_qualified_name": "TIPviUeJtLH",
  "il2cpp_type_get_reflection_name": "zTuKaJu_LQR",
  "il2cpp_type_is_static": "VcOEqrZWRgC",
  "il2cpp_type_is_pointer_type": "OBJroSS_Tff",
  "il2cpp_image_get_assembly": "AEmCqBunjly",
  "il2cpp_image_get_name": "EbjnMNwvoiX",
  "il2cpp_image_get_filename": "NlKlgJfFcKV",
  "il2cpp_image_get_entry_point": "ZdRuoooiDxf",
  "il2cpp_image_get_class_count": "IYlKjOUPozu",
  "il2cpp_image_get_class": "vNrpMmGRLvx",
  "il2cpp_capture_memory_snapshot": "eAaWivAWOBk",
  "il2cpp_free_captured_memory_snapshot": "uTArgxzivIU",
  "il2cpp_set_find_plugin_callback": "_flqfwaYxiY",
  "il2cpp_register_log_callback": "egnySaxHksf",
  "il2cpp_debugger_set_agent_options": "vjSXxzesGTt",
  "il2cpp_is_debugger_attached": "rhHztYo_EBO",
  "il2cpp_register_debugger_agent_transport": "nqQzlzenNwA",
  "il2cpp_debug_foreach_method": "_dirBj_FaLx",
  "il2cpp_debug_get_method_info": "izacVXNyNNX",
  "il2cpp_unity_install_unitytls_interface": "NuYYmuyCHBb",
  "il2cpp_custom_attrs_from_class": "iJvCWwdSQZd",
  "il2cpp_custom_attrs_from_method": "SkcdgpsVmdi",
  "il2cpp_custom_attrs_from_field": "fkeXYujsvXZ",
  "il2cpp_custom_attrs_get_attr": "j_eXqJDIEyA",
  "il2cpp_custom_attrs_has_attr": "NMdueOXdKaP",
  "il2cpp_custom_attrs_construct": "ASbEkHybNjv",
  "il2cpp_custom_attrs_free": "QKgrcACzNhN",
  "il2cpp_class_set_userdata": "UPlZiLXgeoq",
  "il2cpp_class_get_userdata_offset": "LhlftatHiwd",
  "il2cpp_set_default_thread_affinity": "ZYrSDMgClJj",
  "il2cpp_unity_set_android_network_up_state_func": "LwPtAVOiuUs"
}